narrow/__init__.py
narrow/_base.py
narrow/cli.py
narrow/configuration.py
narrow/exceptions.py
narrow/plotting.py
narrow/shortcuts.py
narrow/utils.py
narrow/apps/__init__.py
narrow/apps/_base.py
narrow/apps/bottle.py
narrow/apps/cherrypy.py
narrow/apps/django.py
narrow/apps/flask.py
narrow/apps/py.py
narrow/apps/entrypoints/__init__.py
narrow/apps/entrypoints/bottle_app.py
narrow/apps/entrypoints/cherrypy_app.py
narrow/apps/entrypoints/django_app.py
narrow/apps/entrypoints/flask_app.py
narrow/apps/entrypoints/py_app.py
narrow/benchers/__init__.py
narrow/benchers/_base.py
narrow/benchers/h2load.py
narrow/benchers/weighttp.py
narrow/files/test.cer
narrow/files/test.pem
narrow/files/test.pub
narrow/files/testnopass.pem
narrow/stands/__init__.py
narrow/stands/_base.py
narrow/stands/nginx.py
narrow/stands/uwsgi.py
narrow-0.1.0.dist-info/DESCRIPTION.rst
narrow-0.1.0.dist-info/METADATA
narrow-0.1.0.dist-info/RECORD
narrow-0.1.0.dist-info/WHEEL
narrow-0.1.0.dist-info/entry_points.txt
narrow-0.1.0.dist-info/metadata.json
narrow-0.1.0.dist-info/top_level.txt
