Metadata-Version: 2.0
Name: narrow
Version: 0.1.0
Summary: Naive throughput measurements for Python web apps and servers
Home-page: https://github.com/idlesign/narrow
Author: Igor Starikov
Author-email: idlesign@yandex.ru
License: BSD 3-Clause License
Platform: UNKNOWN
Classifier: Development Status :: 4 - Beta
Classifier: Operating System :: OS Independent
Classifier: Programming Language :: Python
Classifier: Programming Language :: Python :: 3
Classifier: Programming Language :: Python :: 3.5
Classifier: Programming Language :: Python :: 3.6
Classifier: License :: OSI Approved :: BSD License
Requires-Dist: click
Requires-Dist: colorhash
Requires-Dist: envbox
Requires-Dist: plotly
Requires-Dist: uwsgi
Requires-Dist: uwsgiconf (>=0.14.2)
